LICENSE
README.md
setup.py
trading_view_scraper_in/__init__.py
trading_view_scraper_in.egg-info/PKG-INFO
trading_view_scraper_in.egg-info/SOURCES.txt
trading_view_scraper_in.egg-info/dependency_links.txt
trading_view_scraper_in.egg-info/requires.txt
trading_view_scraper_in.egg-info/top_level.txt