Metadata-Version: 2.1
Name: trading-view-scraper-in
Version: 1.0.0
Summary: A python library to scrape TradingView.
Home-page: UNKNOWN
Author: DataKund
Author-email: datakund@gmail.com
License: Apache License 2.0
Keywords: tradingview,python,bot_studio,automation,search,scraper,scrape
Platform: UNKNOWN
License-File: LICENSE
